README.md
setup.py
smartdict/__init__.py
smartdict/function.py
smartdict/path.py
smartdict/resolver.py
smartdict/roba.py
smartdict/smartdict.py
smartdict.egg-info/PKG-INFO
smartdict.egg-info/SOURCES.txt
smartdict.egg-info/dependency_links.txt
smartdict.egg-info/top_level.txt