Metadata-Version: 2.4
Name: smartdict
Version: 0.3.2
Summary: A reference resolver for nested dictionaries that supports default values, partial references, and circular dependency detection.
Home-page: https://github.com/Jyonn/smartdict
Author: Jyonn Liu
Author-email: i@6-79.cn
License: MIT Licence
Keywords: dict,reference
Platform: any
Dynamic: author
Dynamic: author-email
Dynamic: description
Dynamic: description-content-type
Dynamic: home-page
Dynamic: keywords
Dynamic: license
Dynamic: platform
Dynamic: summary
